pushbullet/__init__.py
pushbullet/__main__.py
pushbullet/pushbullet.py
python_pushbullet-1.0.0.dist-info/LICENCE
python_pushbullet-1.0.0.dist-info/METADATA
python_pushbullet-1.0.0.dist-info/WHEEL
python_pushbullet-1.0.0.dist-info/entry_points.txt
python_pushbullet-1.0.0.dist-info/top_level.txt
python_pushbullet-1.0.0.dist-info/RECORD
