Metadata-Version: 2.1
Name: python-pushbullet
Version: 1.0.0
Summary: A python module for interacting with the v2 Pushbullet API.
Home-page: https://github.com/dylan-robins/python-pushbullet
Author: Dylan Robins
Author-email: dylan.robins@gmail.com
License: GPL-3.0
Platform: UNKNOWN
Classifier: License :: OSI Approved :: GNU General Public License v3 (GPLv3)
Classifier: Programming Language :: Python :: 3
Classifier: Programming Language :: Python :: 3.6
Classifier: Programming Language :: Python :: 3.7
Classifier: Programming Language :: Python :: 3.8
Classifier: Programming Language :: Python :: 3.9
License-File: LICENCE
Requires-Dist: requests (==2.26.0)
Requires-Dist: python-dotenv (==0.19.0)
